faust_avro_serializer/__init__.py
faust_avro_serializer/avro_serializer.py
faust_avro_serializer-1.2.0.dist-info/LICENSE
faust_avro_serializer-1.2.0.dist-info/WHEEL
faust_avro_serializer-1.2.0.dist-info/METADATA
faust_avro_serializer-1.2.0.dist-info/RECORD
